{
    "name": "LoadPagePiece",
    "description": "Go to web page for given url",
    "dependency": {
        "requirements_file": "requirements_0.txt"
    },
    "container_resources": {
        "requests": {
            "cpu": 100,
            "memory": 128
        },
        "limits": {
            "cpu": 500,
            "memory": 512
        }
    },
    "tags": [
        "selenium",
        "web-browser"
    ],
    "style": {
        "node_label": "Load URL",
        "icon_class_name": "fa-solid fa-globe-pointer"
    }
}